cartesianPlane/__init__.py
cartesianPlane/cartesianObjects.py
cartesianPlane/colors.py
cartesian_plane-1.0.1.dist-info/LICENSE
cartesian_plane-1.0.1.dist-info/METADATA
cartesian_plane-1.0.1.dist-info/WHEEL
cartesian_plane-1.0.1.dist-info/top_level.txt
cartesian_plane-1.0.1.dist-info/RECORD
