Metadata-Version: 2.1
Name: cartesian-plane
Version: 1.0.1
Summary: Provides a cartesian plane canvas able to move and zooming in pygame.
Author-email: murilo-henrique060 <henrique.henryconde@gmail.com>
License: MIT License
Project-URL: Homepage, https://github.com/murilo-henrique060/Cartesian-Plane
Keywords: cartesian plane,pygame,canvas
Classifier: License :: OSI Approved :: MIT License
Classifier: Programming Language :: Python :: 3
Requires-Python: >=3.10
License-File: LICENSE
